odoo8_addon_l10n_es_aeat_mod347-8.0.1.5.0-py2.7-nspkg.pth
odoo8_addon_l10n_es_aeat_mod347-8.0.1.5.0.dist-info/DESCRIPTION.rst
odoo8_addon_l10n_es_aeat_mod347-8.0.1.5.0.dist-info/METADATA
odoo8_addon_l10n_es_aeat_mod347-8.0.1.5.0.dist-info/RECORD
odoo8_addon_l10n_es_aeat_mod347-8.0.1.5.0.dist-info/WHEEL
odoo8_addon_l10n_es_aeat_mod347-8.0.1.5.0.dist-info/metadata.json
odoo8_addon_l10n_es_aeat_mod347-8.0.1.5.0.dist-info/namespace_packages.txt
odoo8_addon_l10n_es_aeat_mod347-8.0.1.5.0.dist-info/top_level.txt
odoo_addons/l10n_es_aeat_mod347/README.rst
odoo_addons/l10n_es_aeat_mod347/__init__.py
odoo_addons/l10n_es_aeat_mod347/__openerp__.py
odoo_addons/l10n_es_aeat_mod347/hooks.py
odoo_addons/l10n_es_aeat_mod347/docs/BOE-A-2014-9740.pdf
odoo_addons/l10n_es_aeat_mod347/i18n/bg.po
odoo_addons/l10n_es_aeat_mod347/i18n/ca.po
odoo_addons/l10n_es_aeat_mod347/i18n/cs.po
odoo_addons/l10n_es_aeat_mod347/i18n/es.po
odoo_addons/l10n_es_aeat_mod347/i18n/es_CO.po
odoo_addons/l10n_es_aeat_mod347/i18n/es_CR.po
odoo_addons/l10n_es_aeat_mod347/i18n/eu.po
odoo_addons/l10n_es_aeat_mod347/i18n/fr.po
odoo_addons/l10n_es_aeat_mod347/i18n/gl.po
odoo_addons/l10n_es_aeat_mod347/i18n/hr.po
odoo_addons/l10n_es_aeat_mod347/i18n/l10n_es_aeat_mod347.pot
odoo_addons/l10n_es_aeat_mod347/i18n/nl.po
odoo_addons/l10n_es_aeat_mod347/i18n/pl.po
odoo_addons/l10n_es_aeat_mod347/i18n/pt.po
odoo_addons/l10n_es_aeat_mod347/i18n/pt_BR.po
odoo_addons/l10n_es_aeat_mod347/i18n/ru.po
odoo_addons/l10n_es_aeat_mod347/i18n/sl.po
odoo_addons/l10n_es_aeat_mod347/i18n/sv.po
odoo_addons/l10n_es_aeat_mod347/i18n/tr.po
odoo_addons/l10n_es_aeat_mod347/i18n/vi.po
odoo_addons/l10n_es_aeat_mod347/images/l10n_es_aeat_mod347.png
odoo_addons/l10n_es_aeat_mod347/models/__init__.py
odoo_addons/l10n_es_aeat_mod347/models/account_invoice.py
odoo_addons/l10n_es_aeat_mod347/models/account_period.py
odoo_addons/l10n_es_aeat_mod347/models/mod347.py
odoo_addons/l10n_es_aeat_mod347/models/res_partner.py
odoo_addons/l10n_es_aeat_mod347/report/mod347_report.rml
odoo_addons/l10n_es_aeat_mod347/report/mod347_report.xml
odoo_addons/l10n_es_aeat_mod347/security/ir.model.access.csv
odoo_addons/l10n_es_aeat_mod347/security/mod_347_security.xml
odoo_addons/l10n_es_aeat_mod347/static/description/icon.png
odoo_addons/l10n_es_aeat_mod347/static/description/icon_source.svg
odoo_addons/l10n_es_aeat_mod347/views/account_invoice_view.xml
