Metadata-Version: 2.0
Name: odoo8-addon-l10n-es-aeat-mod347
Version: 8.0.1.5.0
Summary: Modelo 347 AEAT
Home-page: https://github.com/OCA/l10n-spain
Author: Pexego,ASR-OSS,NaN·tic,Acysos,Serv. Tecnol. Avanzados - Pedro M. Baeza,Antiun Ingeniería S.L.,Odoo Community Association (OCA)
Author-email: support@odoo-community.org
License: AGPL-3
Platform: UNKNOWN
Classifier: Programming Language :: Python :: 2.7
Classifier: Framework :: Odoo
Classifier: License :: OSI Approved :: GNU Affero General Public License v3
Requires-Dist: odoo (<9.0a,>=8.0a)
Requires-Dist: odoo8-addon-account-invoice-currency
Requires-Dist: odoo8-addon-l10n-es-aeat
